semlib/__about__.py
semlib/__init__.py
semlib/apply.py
semlib/bare.py
semlib/box.py
semlib/cache.py
semlib/compare.py
semlib/extrema.py
semlib/filter.py
semlib/find.py
semlib/map.py
semlib/prompt.py
semlib/py.typed
semlib/reduce.py
semlib/session.py
semlib/_internal/__init__.py
semlib/_internal/base.py
semlib/_internal/constants.py
semlib/_internal/util.py
semlib/sort/__init__.py
semlib/sort/sort.py
semlib/sort/algorithm/__init__.py
semlib/sort/algorithm/algorithm.py
semlib/sort/algorithm/borda_count.py
semlib/sort/algorithm/quicksort.py
semlib-1.0.0.dist-info/METADATA
semlib-1.0.0.dist-info/WHEEL
semlib-1.0.0.dist-info/licenses/LICENSE.md
semlib-1.0.0.dist-info/RECORD
