Metadata-Version: 2.4
Name: semlib
Version: 1.0.0
Summary: Data processing and analysis pipelines with LLMs
Project-URL: homepage, https://github.com/anishathalye/semlib
Project-URL: repository, https://github.com/anishathalye/semlib.git
Project-URL: issues, https://github.com/anishathalye/semlib/issues
Author-email: Anish Athalye <me@anishathalye.com>
License-File: LICENSE.md
Classifier: Development Status :: 4 - Beta
Classifier: Intended Audience :: Developers
Classifier: License :: OSI Approved :: MIT License
Classifier: Programming Language :: Python :: 3
Classifier: Programming Language :: Python :: 3.12
Classifier: Programming Language :: Python :: 3.13
Classifier: Topic :: Utilities
Requires-Python: >=3.12
Requires-Dist: litellm<2,>=1.75
Requires-Dist: pydantic<3,>=2.5
